{
    "version": "1.2.1",
    "architecture": {
        "32bit": {
            "url": "https://github.com/gabrielrobert/xavtool/releases/download/1.2.1/xavtool_1.2.1_windows_32-bit.tar.gz",
            "bin": "xavtool.exe",
            "hash": "d899ae55a3551c8148071fe22dfae8437058c5180a34fece78200ce203a670e0"
        },
        "64bit": {
            "url": "https://github.com/gabrielrobert/xavtool/releases/download/1.2.1/xavtool_1.2.1_windows_64-bit.tar.gz",
            "bin": "xavtool.exe",
            "hash": "ad8f5282e365b0eed8660d90f8de4bc991919d9cd233607e44386f4075c42c43"
        }
    },
    "homepage": "https://github.com/gabrielrobert/xavtool",
    "license": "MIT",
    "description": "Xplat Automating Version Tool"
}